spektralwerk_scpi_client/__init__.py
spektralwerk_scpi_client/exceptions.py
spektralwerk_scpi_client/py.typed
spektralwerk_scpi_client/devices/__init__.py
spektralwerk_scpi_client/devices/spektralwerk_core.py
spektralwerk_scpi_client/scpi/__init__.py
spektralwerk_scpi_client/scpi/commands.py
spektralwerk_scpi_client/scpi/mnemonics.py
spektralwerk_scpi_client/scpi/units.py
spektralwerk_scpi_client-0.3.2.dist-info/METADATA
spektralwerk_scpi_client-0.3.2.dist-info/WHEEL
spektralwerk_scpi_client-0.3.2.dist-info/licenses/LICENSE
spektralwerk_scpi_client-0.3.2.dist-info/RECORD
