Metadata-Version: 2.4
Name: spektralwerk_scpi_client
Version: 0.3.2
Summary: Spektralwerk SCPI communication library
License-Expression: MIT
License-File: LICENSE
Keywords: SCPI,Spektralwerk
Classifier: Programming Language :: Python
Requires-Python: >=3.8
Requires-Dist: pyvisa-py>=0.8.0
Requires-Dist: pyvisa>=1.15.0
